moleculib/__init__.py
moleculib/abstract/__init__.py
moleculib/abstract/dataset.py
moleculib/abstract/metrics.py
moleculib/abstract/transform.py
moleculib/assembly/__init__.py
moleculib/assembly/dataset.py
moleculib/assembly/datum.py
moleculib/assembly/metrics.py
moleculib/assembly/transform.py
moleculib/molecule/__init__.py
moleculib/molecule/_build_all.py
moleculib/molecule/alphabet.py
moleculib/molecule/batch.py
moleculib/molecule/dataset.py
moleculib/molecule/datum.py
moleculib/molecule/h5_to_pdb.py
moleculib/molecule/transform.py
moleculib/molecule/utils.py
moleculib/molecule/tests/__init__.py
moleculib/molecule/tests/loader_test.py
moleculib/nucleic/__init__.py
moleculib/nucleic/alphabet.py
moleculib/nucleic/batch.py
moleculib/nucleic/dataset.py
moleculib/nucleic/datum.py
moleculib/nucleic/transform.py
moleculib/nucleic/utils.py
moleculib/protein/__init__.py
moleculib/protein/alphabet.py
moleculib/protein/batch.py
moleculib/protein/dataset.py
moleculib/protein/datum.py
moleculib/protein/jax_utils.py
moleculib/protein/measures.py
moleculib/protein/metrics.py
moleculib/protein/transform.py
moleculib/protein/utils.py
moleculib/protein/tests/__init__.py
moleculib/protein/tests/loader_test.py
moleculib/sequence/__init__.py
moleculib/sequence/dataset.py
moleculib/sequence/datum.py
moleculib/sequence/metrics.py
moleculib/sequence/transform.py
moleculib/sequence/utils.py
moleculib/traj/__init__.py
moleculib/traj/dataset.py
moleculib-0.1.0.dist-info/LICENSE
moleculib-0.1.0.dist-info/METADATA
moleculib-0.1.0.dist-info/WHEEL
moleculib-0.1.0.dist-info/top_level.txt
moleculib-0.1.0.dist-info/RECORD
