Metadata-Version: 2.1
Name: moleculib
Version: 0.1.0
Summary: Molecule library
Home-page: UNKNOWN
License: UNKNOWN
Platform: UNKNOWN
Classifier: Programming Language :: Python :: 3.7
Requires-Python: >=3.7
Requires-Dist: numpy
Requires-Dist: einops
Requires-Dist: ordered-set
Requires-Dist: biopython
Requires-Dist: biotite
Requires-Dist: pandas
Requires-Dist: tqdm
Requires-Dist: mendeleev
Requires-Dist: py3Dmol
Requires-Dist: rdkit
Requires-Dist: plotly
Requires-Dist: mdtraj
